QtTitlebar/QtTitlebar.dll
QtTitlebar/__init__.py
qttitlebar-1.0.0.dist-info/licenses/LICENSE
qttitlebar-1.0.0.dist-info/METADATA
qttitlebar-1.0.0.dist-info/WHEEL
qttitlebar-1.0.0.dist-info/top_level.txt
qttitlebar-1.0.0.dist-info/RECORD
